shukujitsu/__init__.py
shukujitsu/__main__.py
shukujitsu/data.py
shukujitsu/exports.py
shukujitsu/holidays.py
shukujitsu/__pycache__/__init__.cpython-312.opt-1.pyc
shukujitsu/__pycache__/__main__.cpython-312.opt-1.pyc
shukujitsu/__pycache__/data.cpython-312.opt-1.pyc
shukujitsu/__pycache__/exports.cpython-312.opt-1.pyc
shukujitsu/__pycache__/holidays.cpython-312.opt-1.pyc
shukujitsu/asof20201118/__init__.py
shukujitsu/asof20201118/syukujitsu.csv
shukujitsu/asof20201118/__pycache__/__init__.cpython-312.opt-1.pyc
shukujitsu/asof20201127/__init__.py
shukujitsu/asof20201127/syukujitsu.csv
shukujitsu/asof20201127/__pycache__/__init__.cpython-312.opt-1.pyc
shukujitsu/asof20210201/__init__.py
shukujitsu/asof20210201/syukujitsu.csv
shukujitsu/asof20210201/__pycache__/__init__.cpython-312.opt-1.pyc
shukujitsu/asof20220201/__init__.py
shukujitsu/asof20220201/syukujitsu.csv
shukujitsu/asof20220201/__pycache__/__init__.cpython-312.opt-1.pyc
shukujitsu/asof20230201/__init__.py
shukujitsu/asof20230201/shukujitsu.csv
shukujitsu/asof20230201/__pycache__/__init__.cpython-312.opt-1.pyc
shukujitsu/asof20230204/__init__.py
shukujitsu/asof20230204/syukujitsu.csv
shukujitsu/asof20230204/__pycache__/__init__.cpython-312.opt-1.pyc
shukujitsu/asof20240717/__init__.py
shukujitsu/asof20240717/syukujitsu.csv
shukujitsu/asof20240717/__pycache__/__init__.cpython-312.opt-1.pyc
python_shukujitsu-2024.7.17.post1.dist-info/LICENSE
python_shukujitsu-2024.7.17.post1.dist-info/METADATA
python_shukujitsu-2024.7.17.post1.dist-info/WHEEL
python_shukujitsu-2024.7.17.post1.dist-info/entry_points.txt
python_shukujitsu-2024.7.17.post1.dist-info/top_level.txt
python_shukujitsu-2024.7.17.post1.dist-info/RECORD
