Metadata-Version: 2.1
Name: python-shukujitsu
Version: 2024.7.17.post1
Summary: Python Japanese holidays library based on static data published by Cabinet Office, Government of Japan
Home-page: https://github.com/sakurai-youhei/python-shukujitsu
Author: Youhei Sakurai
Author-email: sakurai.youhei@gmail.com
Maintainer: Youhei Sakurai
Maintainer-email: sakurai.youhei@gmail.com
License: MIT
Platform: any
Classifier: Intended Audience :: Developers
Classifier: License :: OSI Approved :: MIT License
Classifier: Natural Language :: Japanese
Classifier: Operating System :: OS Independent
Classifier: Programming Language :: Python
Classifier: Programming Language :: Python :: 3
Classifier: Programming Language :: Python :: 3.8
Classifier: Programming Language :: Python :: 3.9
Classifier: Programming Language :: Python :: 3.10
Classifier: Programming Language :: Python :: 3.11
Classifier: Programming Language :: Python :: 3.12
Requires-Python: >=3
License-File: LICENSE
Requires-Dist: python-dateutil
